sz_semantics/__init__.py
sz_semantics/mask.py
sz_semantics/namespace/__init__.py
sz_semantics/sem.py
sz_semantics/sz.py
sz_semantics/util.py
sz_semantics-1.3.3.dist-info/LICENSE
sz_semantics-1.3.3.dist-info/METADATA
sz_semantics-1.3.3.dist-info/WHEEL
sz_semantics-1.3.3.dist-info/RECORD
