Metadata-Version: 2.3
Name: sz_semantics
Version: 1.3.3
Summary: Transform JSON output from Senzing SDK for use with graph technologies, semantics, and downstream LLM integrations
License: MIT
Keywords: bods,context engineering,data privacy,entity resolution,entity resolved knowledge graph,followthemoney,grpc,information exchange,niem,ontology,rdf,semantic layer,semantics,skos,taxonomy,thesaurus,worldcat
Author: Paco Nathan
Author-email: paco@senzing.com
Requires-Python: >=3.11
Classifier: Programming Language :: Python
Classifier: Programming Language :: Python :: 3 :: Only
Classifier: Programming Language :: Python :: 3.11
Classifier: Programming Language :: Python :: 3.12
Classifier: Programming Language :: Python :: 3.13
Classifier: Programming Language :: Python :: 3.14
Classifier: Operating System :: OS Independent
Classifier: License :: OSI Approved :: MIT License
Classifier: Development Status :: 5 - Production/Stable
Classifier: Intended Audience :: Developers
Classifier: Intended Audience :: Education
Classifier: Intended Audience :: Information Technology
Classifier: Intended Audience :: Science/Research
Classifier: Topic :: Scientific/Engineering :: Artificial Intelligence
Classifier: Topic :: Scientific/Engineering :: Human Machine Interfaces
Classifier: Topic :: Scientific/Engineering :: Information Analysis
Classifier: Topic :: Software Development :: Libraries :: Python Modules
Classifier: Topic :: Text Processing :: Indexing
Requires-Dist: rdflib (>=7.2.1,<8.0.0)
Requires-Dist: senzing-grpc (==0.5.11)
Project-URL: Homepage, https://github.com/senzing-garage/sz-semantics
Project-URL: package, https://pypi.org/project/sz_semantics/
Project-URL: semantics, https://github.com/senzing-garage/sz-semantics/wiki/ns
Project-URL: tutorial, https://github.com/DerwenAI/cdl-2025-masterclass
